[{"user_id": "f6829a66-7009-42bb-9d91-17add53fcc33", "is_bot": false, "ts": 0, "event": "Position", "pixel_x": 323.04, "pixel_y": 397.51}, {"user_id": "f6829a66-7009-42bb-9d91-17add53fcc33", "is_bot": false, "ts": 15000, "event": "Position", "pixel_x": 341.15, "pixel_y": 373.57}, {"user_id": "f6829a66-7009-42bb-9d91-17add53fcc33", "is_bot": false, "ts": 20000, "event": "Position", "pixel_x": 329.11, "pixel_y": 352.74}, {"user_id": "f6829a66-7009-42bb-9d91-17add53fcc33", "is_bot": false, "ts": 26000, "event": "Position", "pixel_x": 361.58, "pixel_y": 311.06}, {"user_id": "f6829a66-7009-42bb-9d91-17add53fcc33", "is_bot": false, "ts": 31000, "event": "Position", "pixel_x": 339.05, "pixel_y": 305.5}, {"user_id": "f6829a66-7009-42bb-9d91-17add53fcc33", "is_bot": false, "ts": 36000, "event": "Position", "pixel_x": 312.54, "pixel_y": 281.57}, {"user_id": "f6829a66-7009-42bb-9d91-17add53fcc33", "is_bot": false, "ts": 41000, "event": "Position", "pixel_x": 331.44, "pixel_y": 243.76}, {"user_id": "f6829a66-7009-42bb-9d91-17add53fcc33", "is_bot": false, "ts": 46000, "event": "Position", "pixel_x": 339.71, "pixel_y": 236.43}, {"user_id": "f6829a66-7009-42bb-9d91-17add53fcc33", "is_bot": false, "ts": 51000, "event": "Position", "pixel_x": 366.21, "pixel_y": 223.47}, {"user_id": "f6829a66-7009-42bb-9d91-17add53fcc33", "is_bot": false, "ts": 56000, "event": "Position", "pixel_x": 371.86, "pixel_y": 241.79}, {"user_id": "f6829a66-7009-42bb-9d91-17add53fcc33", "is_bot": false, "ts": 61000, "event": "Position", "pixel_x": 401.25, "pixel_y": 270.2}, {"user_id": "f6829a66-7009-42bb-9d91-17add53fcc33", "is_bot": false, "ts": 66000, "event": "Position", "pixel_x": 399.47, "pixel_y": 312.04}, {"user_id": "f6829a66-7009-42bb-9d91-17add53fcc33", "is_bot": false, "ts": 71000, "event": "Position", "pixel_x": 397.13, "pixel_y": 320.03}, {"user_id": "f6829a66-7009-42bb-9d91-17add53fcc33", "is_bot": false, "ts": 76000, "event": "Position", "pixel_x": 391.65, "pixel_y": 319.0}, {"user_id": "f6829a66-7009-42bb-9d91-17add53fcc33", "is_bot": false, "ts": 81000, "event": "Position", "pixel_x": 376.04, "pixel_y": 340.2}, {"user_id": "f6829a66-7009-42bb-9d91-17add53fcc33", "is_bot": false, "ts": 86000, "event": "Position", "pixel_x": 376.77, "pixel_y": 345.57}, {"user_id": "f6829a66-7009-42bb-9d91-17add53fcc33", "is_bot": false, "ts": 91000, "event": "Position", "pixel_x": 352.76, "pixel_y": 355.61}, {"user_id": "f6829a66-7009-42bb-9d91-17add53fcc33", "is_bot": false, "ts": 96000, "event": "Position", "pixel_x": 355.65, "pixel_y": 353.82}, {"user_id": "f6829a66-7009-42bb-9d91-17add53fcc33", "is_bot": false, "ts": 101000, "event": "Position", "pixel_x": 355.42, "pixel_y": 358.65}, {"user_id": "f6829a66-7009-42bb-9d91-17add53fcc33", "is_bot": false, "ts": 106000, "event": "Position", "pixel_x": 348.94, "pixel_y": 355.47}, {"user_id": "f6829a66-7009-42bb-9d91-17add53fcc33", "is_bot": false, "ts": 116000, "event": "BotKill", "pixel_x": 351.3, "pixel_y": 380.44}, {"user_id": "f6829a66-7009-42bb-9d91-17add53fcc33", "is_bot": false, "ts": 116000, "event": "Position", "pixel_x": 352.42, "pixel_y": 381.07}, {"user_id": "f6829a66-7009-42bb-9d91-17add53fcc33", "is_bot": false, "ts": 121000, "event": "Position", "pixel_x": 350.48, "pixel_y": 380.18}, {"user_id": "f6829a66-7009-42bb-9d91-17add53fcc33", "is_bot": false, "ts": 121000, "event": "BotKill", "pixel_x": 350.77, "pixel_y": 381.13}, {"user_id": "f6829a66-7009-42bb-9d91-17add53fcc33", "is_bot": false, "ts": 122000, "event": "BotKill", "pixel_x": 350.77, "pixel_y": 381.13}, {"user_id": "f6829a66-7009-42bb-9d91-17add53fcc33", "is_bot": false, "ts": 141000, "event": "Position", "pixel_x": 352.7, "pixel_y": 384.53}, {"user_id": "f6829a66-7009-42bb-9d91-17add53fcc33", "is_bot": false, "ts": 143000, "event": "Loot", "pixel_x": 351.76, "pixel_y": 391.24}, {"user_id": "f6829a66-7009-42bb-9d91-17add53fcc33", "is_bot": false, "ts": 144000, "event": "Loot", "pixel_x": 351.47, "pixel_y": 390.96}, {"user_id": "f6829a66-7009-42bb-9d91-17add53fcc33", "is_bot": false, "ts": 146000, "event": "Position", "pixel_x": 352.67, "pixel_y": 399.32}, {"user_id": "f6829a66-7009-42bb-9d91-17add53fcc33", "is_bot": false, "ts": 148000, "event": "Loot", "pixel_x": 352.27, "pixel_y": 410.61}, {"user_id": "f6829a66-7009-42bb-9d91-17add53fcc33", "is_bot": false, "ts": 149000, "event": "Loot", "pixel_x": 352.84, "pixel_y": 410.05}, {"user_id": "f6829a66-7009-42bb-9d91-17add53fcc33", "is_bot": false, "ts": 150000, "event": "Loot", "pixel_x": 352.84, "pixel_y": 410.05}, {"user_id": "f6829a66-7009-42bb-9d91-17add53fcc33", "is_bot": false, "ts": 151000, "event": "Position", "pixel_x": 356.05, "pixel_y": 415.92}, {"user_id": "f6829a66-7009-42bb-9d91-17add53fcc33", "is_bot": false, "ts": 152000, "event": "Loot", "pixel_x": 356.45, "pixel_y": 418.17}, {"user_id": "f6829a66-7009-42bb-9d91-17add53fcc33", "is_bot": false, "ts": 152000, "event": "Loot", "pixel_x": 356.45, "pixel_y": 418.17}, {"user_id": "f6829a66-7009-42bb-9d91-17add53fcc33", "is_bot": false, "ts": 156000, "event": "Position", "pixel_x": 346.01, "pixel_y": 431.39}, {"user_id": "f6829a66-7009-42bb-9d91-17add53fcc33", "is_bot": false, "ts": 161000, "event": "Position", "pixel_x": 384.39, "pixel_y": 437.91}, {"user_id": "f6829a66-7009-42bb-9d91-17add53fcc33", "is_bot": false, "ts": 166000, "event": "Position", "pixel_x": 397.78, "pixel_y": 476.62}, {"user_id": "f6829a66-7009-42bb-9d91-17add53fcc33", "is_bot": false, "ts": 171000, "event": "Position", "pixel_x": 393.23, "pixel_y": 479.94}, {"user_id": "f6829a66-7009-42bb-9d91-17add53fcc33", "is_bot": false, "ts": 176000, "event": "Position", "pixel_x": 390.77, "pixel_y": 472.63}, {"user_id": "f6829a66-7009-42bb-9d91-17add53fcc33", "is_bot": false, "ts": 191000, "event": "Position", "pixel_x": 403.72, "pixel_y": 459.99}, {"user_id": "f6829a66-7009-42bb-9d91-17add53fcc33", "is_bot": false, "ts": 196000, "event": "Position", "pixel_x": 401.26, "pixel_y": 473.1}, {"user_id": "f6829a66-7009-42bb-9d91-17add53fcc33", "is_bot": false, "ts": 203000, "event": "BotKill", "pixel_x": 402.76, "pixel_y": 472.0}, {"user_id": "f6829a66-7009-42bb-9d91-17add53fcc33", "is_bot": false, "ts": 206000, "event": "Loot", "pixel_x": 396.49, "pixel_y": 466.47}, {"user_id": "f6829a66-7009-42bb-9d91-17add53fcc33", "is_bot": false, "ts": 207000, "event": "Position", "pixel_x": 398.01, "pixel_y": 468.04}, {"user_id": "f6829a66-7009-42bb-9d91-17add53fcc33", "is_bot": false, "ts": 212000, "event": "Position", "pixel_x": 382.9, "pixel_y": 483.82}, {"user_id": "f6829a66-7009-42bb-9d91-17add53fcc33", "is_bot": false, "ts": 217000, "event": "Position", "pixel_x": 376.82, "pixel_y": 486.6}, {"user_id": "f6829a66-7009-42bb-9d91-17add53fcc33", "is_bot": false, "ts": 222000, "event": "Position", "pixel_x": 370.7, "pixel_y": 496.43}, {"user_id": "f6829a66-7009-42bb-9d91-17add53fcc33", "is_bot": false, "ts": 223000, "event": "Loot", "pixel_x": 370.7, "pixel_y": 496.43}, {"user_id": "f6829a66-7009-42bb-9d91-17add53fcc33", "is_bot": false, "ts": 227000, "event": "Position", "pixel_x": 347.81, "pixel_y": 508.9}, {"user_id": "f6829a66-7009-42bb-9d91-17add53fcc33", "is_bot": false, "ts": 232000, "event": "Position", "pixel_x": 307.33, "pixel_y": 513.11}, {"user_id": "f6829a66-7009-42bb-9d91-17add53fcc33", "is_bot": false, "ts": 237000, "event": "Position", "pixel_x": 288.27, "pixel_y": 550.79}, {"user_id": "f6829a66-7009-42bb-9d91-17add53fcc33", "is_bot": false, "ts": 242000, "event": "Position", "pixel_x": 272.37, "pixel_y": 592.49}, {"user_id": "f6829a66-7009-42bb-9d91-17add53fcc33", "is_bot": false, "ts": 247000, "event": "Position", "pixel_x": 234.38, "pixel_y": 612.14}, {"user_id": "f6829a66-7009-42bb-9d91-17add53fcc33", "is_bot": false, "ts": 250000, "event": "Loot", "pixel_x": 230.6, "pixel_y": 614.9}, {"user_id": "f6829a66-7009-42bb-9d91-17add53fcc33", "is_bot": false, "ts": 257000, "event": "Position", "pixel_x": 234.5, "pixel_y": 598.34}, {"user_id": "f6829a66-7009-42bb-9d91-17add53fcc33", "is_bot": false, "ts": 262000, "event": "Position", "pixel_x": 217.59, "pixel_y": 605.87}, {"user_id": "f6829a66-7009-42bb-9d91-17add53fcc33", "is_bot": false, "ts": 267000, "event": "Position", "pixel_x": 204.06, "pixel_y": 605.46}, {"user_id": "f6829a66-7009-42bb-9d91-17add53fcc33", "is_bot": false, "ts": 272000, "event": "Position", "pixel_x": 224.22, "pixel_y": 609.51}, {"user_id": "f6829a66-7009-42bb-9d91-17add53fcc33", "is_bot": false, "ts": 276000, "event": "Loot", "pixel_x": 227.19, "pixel_y": 612.21}, {"user_id": "f6829a66-7009-42bb-9d91-17add53fcc33", "is_bot": false, "ts": 277000, "event": "Position", "pixel_x": 227.67, "pixel_y": 611.82}, {"user_id": "f6829a66-7009-42bb-9d91-17add53fcc33", "is_bot": false, "ts": 282000, "event": "Position", "pixel_x": 234.48, "pixel_y": 594.47}, {"user_id": "f6829a66-7009-42bb-9d91-17add53fcc33", "is_bot": false, "ts": 287000, "event": "Position", "pixel_x": 247.42, "pixel_y": 612.94}, {"user_id": "f6829a66-7009-42bb-9d91-17add53fcc33", "is_bot": false, "ts": 292000, "event": "Position", "pixel_x": 257.19, "pixel_y": 632.33}, {"user_id": "f6829a66-7009-42bb-9d91-17add53fcc33", "is_bot": false, "ts": 293000, "event": "Loot", "pixel_x": 257.19, "pixel_y": 632.33}, {"user_id": "f6829a66-7009-42bb-9d91-17add53fcc33", "is_bot": false, "ts": 293000, "event": "Loot", "pixel_x": 257.19, "pixel_y": 632.33}, {"user_id": "f6829a66-7009-42bb-9d91-17add53fcc33", "is_bot": false, "ts": 294000, "event": "Loot", "pixel_x": 257.19, "pixel_y": 632.33}, {"user_id": "f6829a66-7009-42bb-9d91-17add53fcc33", "is_bot": false, "ts": 297000, "event": "Position", "pixel_x": 249.6, "pixel_y": 634.98}, {"user_id": "f6829a66-7009-42bb-9d91-17add53fcc33", "is_bot": false, "ts": 307000, "event": "Position", "pixel_x": 249.74, "pixel_y": 616.12}, {"user_id": "f6829a66-7009-42bb-9d91-17add53fcc33", "is_bot": false, "ts": 312000, "event": "Position", "pixel_x": 250.26, "pixel_y": 624.23}, {"user_id": "f6829a66-7009-42bb-9d91-17add53fcc33", "is_bot": false, "ts": 317000, "event": "Position", "pixel_x": 249.99, "pixel_y": 628.28}, {"user_id": "f6829a66-7009-42bb-9d91-17add53fcc33", "is_bot": false, "ts": 327000, "event": "Position", "pixel_x": 257.36, "pixel_y": 667.27}, {"user_id": "f6829a66-7009-42bb-9d91-17add53fcc33", "is_bot": false, "ts": 332000, "event": "Position", "pixel_x": 266.01, "pixel_y": 701.82}, {"user_id": "f6829a66-7009-42bb-9d91-17add53fcc33", "is_bot": false, "ts": 337000, "event": "Position", "pixel_x": 301.48, "pixel_y": 735.86}, {"user_id": "f6829a66-7009-42bb-9d91-17add53fcc33", "is_bot": false, "ts": 342000, "event": "Position", "pixel_x": 337.94, "pixel_y": 764.53}, {"user_id": "f6829a66-7009-42bb-9d91-17add53fcc33", "is_bot": false, "ts": 347000, "event": "Position", "pixel_x": 379.88, "pixel_y": 788.49}, {"user_id": "f6829a66-7009-42bb-9d91-17add53fcc33", "is_bot": false, "ts": 352000, "event": "Position", "pixel_x": 417.45, "pixel_y": 786.56}, {"user_id": "f6829a66-7009-42bb-9d91-17add53fcc33", "is_bot": false, "ts": 357000, "event": "Position", "pixel_x": 452.93, "pixel_y": 750.95}, {"user_id": "f6829a66-7009-42bb-9d91-17add53fcc33", "is_bot": false, "ts": 362000, "event": "Position", "pixel_x": 433.93, "pixel_y": 724.17}, {"user_id": "f6829a66-7009-42bb-9d91-17add53fcc33", "is_bot": false, "ts": 367000, "event": "Position", "pixel_x": 432.95, "pixel_y": 724.71}, {"user_id": "f6829a66-7009-42bb-9d91-17add53fcc33", "is_bot": false, "ts": 377000, "event": "Position", "pixel_x": 446.93, "pixel_y": 726.35}, {"user_id": "f6829a66-7009-42bb-9d91-17add53fcc33", "is_bot": false, "ts": 383000, "event": "Position", "pixel_x": 473.02, "pixel_y": 681.91}, {"user_id": "f6829a66-7009-42bb-9d91-17add53fcc33", "is_bot": false, "ts": 388000, "event": "Position", "pixel_x": 492.86, "pixel_y": 629.71}, {"user_id": "f6829a66-7009-42bb-9d91-17add53fcc33", "is_bot": false, "ts": 392000, "event": "Loot", "pixel_x": 493.48, "pixel_y": 617.45}, {"user_id": "f6829a66-7009-42bb-9d91-17add53fcc33", "is_bot": false, "ts": 393000, "event": "Position", "pixel_x": 492.22, "pixel_y": 615.28}, {"user_id": "f6829a66-7009-42bb-9d91-17add53fcc33", "is_bot": false, "ts": 401000, "event": "Loot", "pixel_x": 496.69, "pixel_y": 619.95}, {"user_id": "f6829a66-7009-42bb-9d91-17add53fcc33", "is_bot": false, "ts": 402000, "event": "Loot", "pixel_x": 497.71, "pixel_y": 620.69}, {"user_id": "f6829a66-7009-42bb-9d91-17add53fcc33", "is_bot": false, "ts": 403000, "event": "Loot", "pixel_x": 494.82, "pixel_y": 617.89}, {"user_id": "f6829a66-7009-42bb-9d91-17add53fcc33", "is_bot": false, "ts": 403000, "event": "Position", "pixel_x": 494.22, "pixel_y": 617.73}, {"user_id": "f6829a66-7009-42bb-9d91-17add53fcc33", "is_bot": false, "ts": 403000, "event": "Loot", "pixel_x": 496.09, "pixel_y": 613.63}, {"user_id": "f6829a66-7009-42bb-9d91-17add53fcc33", "is_bot": false, "ts": 404000, "event": "Loot", "pixel_x": 496.72, "pixel_y": 614.15}, {"user_id": "f6829a66-7009-42bb-9d91-17add53fcc33", "is_bot": false, "ts": 407000, "event": "BotKill", "pixel_x": 496.5, "pixel_y": 609.32}, {"user_id": "f6829a66-7009-42bb-9d91-17add53fcc33", "is_bot": false, "ts": 408000, "event": "Position", "pixel_x": 496.24, "pixel_y": 608.06}, {"user_id": "f6829a66-7009-42bb-9d91-17add53fcc33", "is_bot": false, "ts": 413000, "event": "Position", "pixel_x": 504.79, "pixel_y": 584.77}, {"user_id": "f6829a66-7009-42bb-9d91-17add53fcc33", "is_bot": false, "ts": 418000, "event": "Position", "pixel_x": 492.53, "pixel_y": 588.66}, {"user_id": "f6829a66-7009-42bb-9d91-17add53fcc33", "is_bot": false, "ts": 422000, "event": "BotKill", "pixel_x": 495.34, "pixel_y": 594.22}, {"user_id": "f6829a66-7009-42bb-9d91-17add53fcc33", "is_bot": false, "ts": 423000, "event": "Position", "pixel_x": 495.03, "pixel_y": 599.57}, {"user_id": "f6829a66-7009-42bb-9d91-17add53fcc33", "is_bot": false, "ts": 425000, "event": "Loot", "pixel_x": 494.89, "pixel_y": 596.51}, {"user_id": "f6829a66-7009-42bb-9d91-17add53fcc33", "is_bot": false, "ts": 427000, "event": "Loot", "pixel_x": 492.87, "pixel_y": 601.52}, {"user_id": "f6829a66-7009-42bb-9d91-17add53fcc33", "is_bot": false, "ts": 427000, "event": "Loot", "pixel_x": 492.87, "pixel_y": 601.52}, {"user_id": "f6829a66-7009-42bb-9d91-17add53fcc33", "is_bot": false, "ts": 428000, "event": "Position", "pixel_x": 492.87, "pixel_y": 601.52}, {"user_id": "f6829a66-7009-42bb-9d91-17add53fcc33", "is_bot": false, "ts": 430000, "event": "Loot", "pixel_x": 497.07, "pixel_y": 609.81}, {"user_id": "f6829a66-7009-42bb-9d91-17add53fcc33", "is_bot": false, "ts": 433000, "event": "Position", "pixel_x": 494.98, "pixel_y": 613.07}, {"user_id": "f6829a66-7009-42bb-9d91-17add53fcc33", "is_bot": false, "ts": 438000, "event": "Position", "pixel_x": 476.16, "pixel_y": 626.26}, {"user_id": "f6829a66-7009-42bb-9d91-17add53fcc33", "is_bot": false, "ts": 443000, "event": "Position", "pixel_x": 442.32, "pixel_y": 605.63}, {"user_id": "f6829a66-7009-42bb-9d91-17add53fcc33", "is_bot": false, "ts": 455000, "event": "Loot", "pixel_x": 442.36, "pixel_y": 606.87}, {"user_id": "f6829a66-7009-42bb-9d91-17add53fcc33", "is_bot": false, "ts": 462000, "event": "Loot", "pixel_x": 442.36, "pixel_y": 606.87}, {"user_id": "f6829a66-7009-42bb-9d91-17add53fcc33", "is_bot": false, "ts": 473000, "event": "Position", "pixel_x": 470.92, "pixel_y": 579.47}, {"user_id": "f6829a66-7009-42bb-9d91-17add53fcc33", "is_bot": false, "ts": 483000, "event": "Position", "pixel_x": 454.79, "pixel_y": 569.11}, {"user_id": "f6829a66-7009-42bb-9d91-17add53fcc33", "is_bot": false, "ts": 488000, "event": "Position", "pixel_x": 455.04, "pixel_y": 589.75}, {"user_id": "f6829a66-7009-42bb-9d91-17add53fcc33", "is_bot": false, "ts": 489000, "event": "Loot", "pixel_x": 455.04, "pixel_y": 589.75}, {"user_id": "f6829a66-7009-42bb-9d91-17add53fcc33", "is_bot": false, "ts": 491000, "event": "Loot", "pixel_x": 456.01, "pixel_y": 589.72}, {"user_id": "f6829a66-7009-42bb-9d91-17add53fcc33", "is_bot": false, "ts": 493000, "event": "Position", "pixel_x": 451.94, "pixel_y": 581.52}, {"user_id": "f6829a66-7009-42bb-9d91-17add53fcc33", "is_bot": false, "ts": 498000, "event": "Position", "pixel_x": 457.74, "pixel_y": 606.66}, {"user_id": "f6829a66-7009-42bb-9d91-17add53fcc33", "is_bot": false, "ts": 503000, "event": "Position", "pixel_x": 462.44, "pixel_y": 604.26}, {"user_id": "f6829a66-7009-42bb-9d91-17add53fcc33", "is_bot": false, "ts": 513000, "event": "Position", "pixel_x": 475.73, "pixel_y": 605.51}, {"user_id": "f6829a66-7009-42bb-9d91-17add53fcc33", "is_bot": false, "ts": 518000, "event": "Position", "pixel_x": 476.71, "pixel_y": 605.8}, {"user_id": "f6829a66-7009-42bb-9d91-17add53fcc33", "is_bot": false, "ts": 523000, "event": "Position", "pixel_x": 470.49, "pixel_y": 611.07}, {"user_id": "f6829a66-7009-42bb-9d91-17add53fcc33", "is_bot": false, "ts": 528000, "event": "Position", "pixel_x": 464.65, "pixel_y": 595.17}, {"user_id": "f6829a66-7009-42bb-9d91-17add53fcc33", "is_bot": false, "ts": 543000, "event": "Position", "pixel_x": 457.37, "pixel_y": 612.13}, {"user_id": "f6829a66-7009-42bb-9d91-17add53fcc33", "is_bot": false, "ts": 548000, "event": "Position", "pixel_x": 458.45, "pixel_y": 630.58}, {"user_id": "f6829a66-7009-42bb-9d91-17add53fcc33", "is_bot": false, "ts": 553000, "event": "Position", "pixel_x": 471.47, "pixel_y": 672.66}, {"user_id": "f6829a66-7009-42bb-9d91-17add53fcc33", "is_bot": false, "ts": 558000, "event": "Position", "pixel_x": 434.02, "pixel_y": 702.18}, {"user_id": "f6829a66-7009-42bb-9d91-17add53fcc33", "is_bot": false, "ts": 564000, "event": "Position", "pixel_x": 383.46, "pixel_y": 708.85}, {"user_id": "f6829a66-7009-42bb-9d91-17add53fcc33", "is_bot": false, "ts": 569000, "event": "Position", "pixel_x": 357.74, "pixel_y": 693.42}, {"user_id": "f6829a66-7009-42bb-9d91-17add53fcc33", "is_bot": false, "ts": 574000, "event": "Position", "pixel_x": 381.3, "pixel_y": 665.14}, {"user_id": "f6829a66-7009-42bb-9d91-17add53fcc33", "is_bot": false, "ts": 579000, "event": "Position", "pixel_x": 385.85, "pixel_y": 617.46}, {"user_id": "f6829a66-7009-42bb-9d91-17add53fcc33", "is_bot": false, "ts": 584000, "event": "Position", "pixel_x": 383.19, "pixel_y": 573.56}, {"user_id": "f6829a66-7009-42bb-9d91-17add53fcc33", "is_bot": false, "ts": 589000, "event": "Position", "pixel_x": 374.34, "pixel_y": 530.64}, {"user_id": "f6829a66-7009-42bb-9d91-17add53fcc33", "is_bot": false, "ts": 594000, "event": "Position", "pixel_x": 359.51, "pixel_y": 484.11}, {"user_id": "f6829a66-7009-42bb-9d91-17add53fcc33", "is_bot": false, "ts": 599000, "event": "Position", "pixel_x": 352.38, "pixel_y": 465.91}, {"user_id": "f6829a66-7009-42bb-9d91-17add53fcc33", "is_bot": false, "ts": 604000, "event": "Position", "pixel_x": 352.19, "pixel_y": 455.42}, {"user_id": "f6829a66-7009-42bb-9d91-17add53fcc33", "is_bot": false, "ts": 609000, "event": "Position", "pixel_x": 353.64, "pixel_y": 410.2}, {"user_id": "f6829a66-7009-42bb-9d91-17add53fcc33", "is_bot": false, "ts": 614000, "event": "Position", "pixel_x": 356.54, "pixel_y": 453.73}, {"user_id": "f6829a66-7009-42bb-9d91-17add53fcc33", "is_bot": false, "ts": 619000, "event": "Position", "pixel_x": 361.77, "pixel_y": 493.25}, {"user_id": "f6829a66-7009-42bb-9d91-17add53fcc33", "is_bot": false, "ts": 624000, "event": "Position", "pixel_x": 375.71, "pixel_y": 532.79}, {"user_id": "f6829a66-7009-42bb-9d91-17add53fcc33", "is_bot": false, "ts": 629000, "event": "Position", "pixel_x": 383.45, "pixel_y": 554.99}, {"user_id": "f6829a66-7009-42bb-9d91-17add53fcc33", "is_bot": false, "ts": 639000, "event": "Position", "pixel_x": 386.54, "pixel_y": 592.64}, {"user_id": "f6829a66-7009-42bb-9d91-17add53fcc33", "is_bot": false, "ts": 644000, "event": "Position", "pixel_x": 391.09, "pixel_y": 618.23}, {"user_id": "f6829a66-7009-42bb-9d91-17add53fcc33", "is_bot": false, "ts": 649000, "event": "Position", "pixel_x": 387.93, "pixel_y": 662.48}, {"user_id": "f6829a66-7009-42bb-9d91-17add53fcc33", "is_bot": false, "ts": 654000, "event": "Position", "pixel_x": 345.37, "pixel_y": 687.67}, {"user_id": "f6829a66-7009-42bb-9d91-17add53fcc33", "is_bot": false, "ts": 659000, "event": "Position", "pixel_x": 308.1, "pixel_y": 699.55}, {"user_id": "f6829a66-7009-42bb-9d91-17add53fcc33", "is_bot": false, "ts": 664000, "event": "Position", "pixel_x": 275.32, "pixel_y": 712.82}]