[{"user_id": "eccd1dc0-1795-4f57-97c5-fcfa0282eec1", "is_bot": false, "ts": 0, "event": "Position", "pixel_x": 61.83, "pixel_y": 481.03}, {"user_id": "eccd1dc0-1795-4f57-97c5-fcfa0282eec1", "is_bot": false, "ts": 25000, "event": "Position", "pixel_x": 77.55, "pixel_y": 477.46}, {"user_id": "eccd1dc0-1795-4f57-97c5-fcfa0282eec1", "is_bot": false, "ts": 30000, "event": "Position", "pixel_x": 92.51, "pixel_y": 451.37}, {"user_id": "eccd1dc0-1795-4f57-97c5-fcfa0282eec1", "is_bot": false, "ts": 35000, "event": "Position", "pixel_x": 85.04, "pixel_y": 423.45}, {"user_id": "eccd1dc0-1795-4f57-97c5-fcfa0282eec1", "is_bot": false, "ts": 40000, "event": "Position", "pixel_x": 89.38, "pixel_y": 410.3}, {"user_id": "eccd1dc0-1795-4f57-97c5-fcfa0282eec1", "is_bot": false, "ts": 45000, "event": "Position", "pixel_x": 98.74, "pixel_y": 407.78}, {"user_id": "eccd1dc0-1795-4f57-97c5-fcfa0282eec1", "is_bot": false, "ts": 47000, "event": "Loot", "pixel_x": 98.74, "pixel_y": 407.78}, {"user_id": "eccd1dc0-1795-4f57-97c5-fcfa0282eec1", "is_bot": false, "ts": 47000, "event": "Loot", "pixel_x": 98.74, "pixel_y": 407.78}, {"user_id": "eccd1dc0-1795-4f57-97c5-fcfa0282eec1", "is_bot": false, "ts": 50000, "event": "Loot", "pixel_x": 106.08, "pixel_y": 405.84}, {"user_id": "eccd1dc0-1795-4f57-97c5-fcfa0282eec1", "is_bot": false, "ts": 50000, "event": "Position", "pixel_x": 106.08, "pixel_y": 405.84}, {"user_id": "eccd1dc0-1795-4f57-97c5-fcfa0282eec1", "is_bot": false, "ts": 56000, "event": "Position", "pixel_x": 95.36, "pixel_y": 411.72}, {"user_id": "eccd1dc0-1795-4f57-97c5-fcfa0282eec1", "is_bot": false, "ts": 61000, "event": "Position", "pixel_x": 93.09, "pixel_y": 416.59}, {"user_id": "eccd1dc0-1795-4f57-97c5-fcfa0282eec1", "is_bot": false, "ts": 63000, "event": "Loot", "pixel_x": 87.96, "pixel_y": 417.94}, {"user_id": "eccd1dc0-1795-4f57-97c5-fcfa0282eec1", "is_bot": false, "ts": 66000, "event": "Position", "pixel_x": 88.38, "pixel_y": 417.94}, {"user_id": "eccd1dc0-1795-4f57-97c5-fcfa0282eec1", "is_bot": false, "ts": 66000, "event": "Loot", "pixel_x": 88.38, "pixel_y": 417.94}, {"user_id": "eccd1dc0-1795-4f57-97c5-fcfa0282eec1", "is_bot": false, "ts": 71000, "event": "Position", "pixel_x": 95.42, "pixel_y": 411.68}, {"user_id": "eccd1dc0-1795-4f57-97c5-fcfa0282eec1", "is_bot": false, "ts": 73000, "event": "Loot", "pixel_x": 90.16, "pixel_y": 407.59}, {"user_id": "eccd1dc0-1795-4f57-97c5-fcfa0282eec1", "is_bot": false, "ts": 76000, "event": "Position", "pixel_x": 84.6, "pixel_y": 406.35}, {"user_id": "eccd1dc0-1795-4f57-97c5-fcfa0282eec1", "is_bot": false, "ts": 81000, "event": "Position", "pixel_x": 88.51, "pixel_y": 388.47}, {"user_id": "eccd1dc0-1795-4f57-97c5-fcfa0282eec1", "is_bot": false, "ts": 86000, "event": "Position", "pixel_x": 102.24, "pixel_y": 385.02}, {"user_id": "eccd1dc0-1795-4f57-97c5-fcfa0282eec1", "is_bot": false, "ts": 91000, "event": "Position", "pixel_x": 94.67, "pixel_y": 394.97}, {"user_id": "eccd1dc0-1795-4f57-97c5-fcfa0282eec1", "is_bot": false, "ts": 91000, "event": "Loot", "pixel_x": 94.67, "pixel_y": 394.97}, {"user_id": "eccd1dc0-1795-4f57-97c5-fcfa0282eec1", "is_bot": false, "ts": 95000, "event": "Loot", "pixel_x": 96.19, "pixel_y": 398.93}, {"user_id": "eccd1dc0-1795-4f57-97c5-fcfa0282eec1", "is_bot": false, "ts": 95000, "event": "Loot", "pixel_x": 96.19, "pixel_y": 398.93}, {"user_id": "eccd1dc0-1795-4f57-97c5-fcfa0282eec1", "is_bot": false, "ts": 101000, "event": "Position", "pixel_x": 124.41, "pixel_y": 401.91}, {"user_id": "eccd1dc0-1795-4f57-97c5-fcfa0282eec1", "is_bot": false, "ts": 106000, "event": "Position", "pixel_x": 129.33, "pixel_y": 407.06}, {"user_id": "eccd1dc0-1795-4f57-97c5-fcfa0282eec1", "is_bot": false, "ts": 111000, "event": "Position", "pixel_x": 148.05, "pixel_y": 397.53}, {"user_id": "eccd1dc0-1795-4f57-97c5-fcfa0282eec1", "is_bot": false, "ts": 112000, "event": "Loot", "pixel_x": 149.98, "pixel_y": 396.12}, {"user_id": "eccd1dc0-1795-4f57-97c5-fcfa0282eec1", "is_bot": false, "ts": 116000, "event": "Position", "pixel_x": 152.34, "pixel_y": 406.78}, {"user_id": "eccd1dc0-1795-4f57-97c5-fcfa0282eec1", "is_bot": false, "ts": 121000, "event": "Position", "pixel_x": 150.87, "pixel_y": 421.47}, {"user_id": "eccd1dc0-1795-4f57-97c5-fcfa0282eec1", "is_bot": false, "ts": 126000, "event": "Position", "pixel_x": 156.1, "pixel_y": 410.6}, {"user_id": "eccd1dc0-1795-4f57-97c5-fcfa0282eec1", "is_bot": false, "ts": 131000, "event": "Position", "pixel_x": 177.1, "pixel_y": 407.95}, {"user_id": "eccd1dc0-1795-4f57-97c5-fcfa0282eec1", "is_bot": false, "ts": 136000, "event": "Position", "pixel_x": 207.03, "pixel_y": 406.41}, {"user_id": "eccd1dc0-1795-4f57-97c5-fcfa0282eec1", "is_bot": false, "ts": 141000, "event": "Position", "pixel_x": 234.09, "pixel_y": 415.55}, {"user_id": "eccd1dc0-1795-4f57-97c5-fcfa0282eec1", "is_bot": false, "ts": 146000, "event": "Position", "pixel_x": 243.62, "pixel_y": 431.56}, {"user_id": "eccd1dc0-1795-4f57-97c5-fcfa0282eec1", "is_bot": false, "ts": 151000, "event": "Position", "pixel_x": 270.67, "pixel_y": 441.28}, {"user_id": "eccd1dc0-1795-4f57-97c5-fcfa0282eec1", "is_bot": false, "ts": 156000, "event": "Position", "pixel_x": 280.66, "pixel_y": 442.87}, {"user_id": "eccd1dc0-1795-4f57-97c5-fcfa0282eec1", "is_bot": false, "ts": 161000, "event": "Position", "pixel_x": 286.74, "pixel_y": 443.93}, {"user_id": "eccd1dc0-1795-4f57-97c5-fcfa0282eec1", "is_bot": false, "ts": 166000, "event": "Position", "pixel_x": 297.23, "pixel_y": 446.3}]