[{"user_id": "d69f4477-9adf-46e3-9aaa-a6646f673347", "is_bot": false, "ts": 0, "event": "Position", "pixel_x": 726.65, "pixel_y": 540.24}, {"user_id": "d69f4477-9adf-46e3-9aaa-a6646f673347", "is_bot": false, "ts": 15000, "event": "Position", "pixel_x": 711.71, "pixel_y": 543.25}, {"user_id": "d69f4477-9adf-46e3-9aaa-a6646f673347", "is_bot": false, "ts": 20000, "event": "Position", "pixel_x": 706.99, "pixel_y": 543.86}, {"user_id": "d69f4477-9adf-46e3-9aaa-a6646f673347", "is_bot": false, "ts": 31000, "event": "Position", "pixel_x": 684.83, "pixel_y": 537.59}, {"user_id": "d69f4477-9adf-46e3-9aaa-a6646f673347", "is_bot": false, "ts": 36000, "event": "Position", "pixel_x": 672.54, "pixel_y": 539.15}, {"user_id": "d69f4477-9adf-46e3-9aaa-a6646f673347", "is_bot": false, "ts": 41000, "event": "Position", "pixel_x": 679.42, "pixel_y": 562.23}, {"user_id": "d69f4477-9adf-46e3-9aaa-a6646f673347", "is_bot": false, "ts": 46000, "event": "Position", "pixel_x": 673.11, "pixel_y": 593.69}, {"user_id": "d69f4477-9adf-46e3-9aaa-a6646f673347", "is_bot": false, "ts": 51000, "event": "Position", "pixel_x": 667.13, "pixel_y": 601.66}, {"user_id": "d69f4477-9adf-46e3-9aaa-a6646f673347", "is_bot": false, "ts": 56000, "event": "Position", "pixel_x": 677.01, "pixel_y": 616.5}, {"user_id": "d69f4477-9adf-46e3-9aaa-a6646f673347", "is_bot": false, "ts": 61000, "event": "Position", "pixel_x": 673.25, "pixel_y": 630.31}, {"user_id": "d69f4477-9adf-46e3-9aaa-a6646f673347", "is_bot": false, "ts": 66000, "event": "Position", "pixel_x": 668.55, "pixel_y": 637.8}, {"user_id": "d69f4477-9adf-46e3-9aaa-a6646f673347", "is_bot": false, "ts": 71000, "event": "Position", "pixel_x": 649.64, "pixel_y": 655.09}, {"user_id": "d69f4477-9adf-46e3-9aaa-a6646f673347", "is_bot": false, "ts": 76000, "event": "Position", "pixel_x": 619.02, "pixel_y": 648.09}, {"user_id": "d69f4477-9adf-46e3-9aaa-a6646f673347", "is_bot": false, "ts": 81000, "event": "Position", "pixel_x": 588.56, "pixel_y": 637.32}, {"user_id": "d69f4477-9adf-46e3-9aaa-a6646f673347", "is_bot": false, "ts": 86000, "event": "Position", "pixel_x": 565.75, "pixel_y": 622.07}, {"user_id": "d69f4477-9adf-46e3-9aaa-a6646f673347", "is_bot": false, "ts": 91000, "event": "Position", "pixel_x": 572.87, "pixel_y": 625.59}, {"user_id": "d69f4477-9adf-46e3-9aaa-a6646f673347", "is_bot": false, "ts": 96000, "event": "Position", "pixel_x": 578.76, "pixel_y": 631.8}, {"user_id": "d69f4477-9adf-46e3-9aaa-a6646f673347", "is_bot": false, "ts": 101000, "event": "Position", "pixel_x": 583.36, "pixel_y": 640.02}, {"user_id": "d69f4477-9adf-46e3-9aaa-a6646f673347", "is_bot": false, "ts": 106000, "event": "Position", "pixel_x": 586.61, "pixel_y": 653.75}, {"user_id": "d69f4477-9adf-46e3-9aaa-a6646f673347", "is_bot": false, "ts": 111000, "event": "Position", "pixel_x": 590.3, "pixel_y": 650.09}, {"user_id": "d69f4477-9adf-46e3-9aaa-a6646f673347", "is_bot": false, "ts": 116000, "event": "Position", "pixel_x": 583.04, "pixel_y": 644.03}, {"user_id": "d69f4477-9adf-46e3-9aaa-a6646f673347", "is_bot": false, "ts": 121000, "event": "Position", "pixel_x": 577.07, "pixel_y": 633.66}, {"user_id": "d69f4477-9adf-46e3-9aaa-a6646f673347", "is_bot": false, "ts": 126000, "event": "Position", "pixel_x": 570.77, "pixel_y": 632.75}, {"user_id": "d69f4477-9adf-46e3-9aaa-a6646f673347", "is_bot": false, "ts": 131000, "event": "Position", "pixel_x": 575.85, "pixel_y": 635.36}, {"user_id": "d69f4477-9adf-46e3-9aaa-a6646f673347", "is_bot": false, "ts": 136000, "event": "Position", "pixel_x": 589.3, "pixel_y": 641.51}, {"user_id": "d69f4477-9adf-46e3-9aaa-a6646f673347", "is_bot": false, "ts": 141000, "event": "Position", "pixel_x": 585.53, "pixel_y": 637.27}, {"user_id": "d69f4477-9adf-46e3-9aaa-a6646f673347", "is_bot": false, "ts": 146000, "event": "Position", "pixel_x": 576.11, "pixel_y": 627.93}, {"user_id": "d69f4477-9adf-46e3-9aaa-a6646f673347", "is_bot": false, "ts": 151000, "event": "Position", "pixel_x": 576.11, "pixel_y": 628.21}, {"user_id": "d69f4477-9adf-46e3-9aaa-a6646f673347", "is_bot": false, "ts": 156000, "event": "Position", "pixel_x": 576.11, "pixel_y": 636.5}, {"user_id": "d69f4477-9adf-46e3-9aaa-a6646f673347", "is_bot": false, "ts": 161000, "event": "Position", "pixel_x": 570.43, "pixel_y": 635.5}, {"user_id": "d69f4477-9adf-46e3-9aaa-a6646f673347", "is_bot": false, "ts": 166000, "event": "Position", "pixel_x": 568.6, "pixel_y": 628.37}, {"user_id": "d69f4477-9adf-46e3-9aaa-a6646f673347", "is_bot": false, "ts": 171000, "event": "Position", "pixel_x": 556.23, "pixel_y": 625.87}, {"user_id": "d69f4477-9adf-46e3-9aaa-a6646f673347", "is_bot": false, "ts": 181000, "event": "Position", "pixel_x": 562.84, "pixel_y": 619.89}, {"user_id": "d69f4477-9adf-46e3-9aaa-a6646f673347", "is_bot": false, "ts": 185000, "event": "BotKill", "pixel_x": 566.93, "pixel_y": 617.87}, {"user_id": "d69f4477-9adf-46e3-9aaa-a6646f673347", "is_bot": false, "ts": 186000, "event": "Position", "pixel_x": 566.4, "pixel_y": 617.86}, {"user_id": "d69f4477-9adf-46e3-9aaa-a6646f673347", "is_bot": false, "ts": 191000, "event": "Position", "pixel_x": 565.39, "pixel_y": 592.27}, {"user_id": "d69f4477-9adf-46e3-9aaa-a6646f673347", "is_bot": false, "ts": 196000, "event": "Position", "pixel_x": 566.16, "pixel_y": 571.71}, {"user_id": "d69f4477-9adf-46e3-9aaa-a6646f673347", "is_bot": false, "ts": 201000, "event": "Position", "pixel_x": 564.66, "pixel_y": 567.81}, {"user_id": "d69f4477-9adf-46e3-9aaa-a6646f673347", "is_bot": false, "ts": 206000, "event": "Position", "pixel_x": 556.17, "pixel_y": 569.71}, {"user_id": "d69f4477-9adf-46e3-9aaa-a6646f673347", "is_bot": false, "ts": 212000, "event": "Position", "pixel_x": 563.09, "pixel_y": 566.69}, {"user_id": "d69f4477-9adf-46e3-9aaa-a6646f673347", "is_bot": false, "ts": 217000, "event": "Position", "pixel_x": 565.44, "pixel_y": 568.09}, {"user_id": "d69f4477-9adf-46e3-9aaa-a6646f673347", "is_bot": false, "ts": 222000, "event": "Position", "pixel_x": 561.61, "pixel_y": 566.5}, {"user_id": "d69f4477-9adf-46e3-9aaa-a6646f673347", "is_bot": false, "ts": 223000, "event": "BotKill", "pixel_x": 562.09, "pixel_y": 565.02}, {"user_id": "d69f4477-9adf-46e3-9aaa-a6646f673347", "is_bot": false, "ts": 227000, "event": "Position", "pixel_x": 563.9, "pixel_y": 567.37}, {"user_id": "d69f4477-9adf-46e3-9aaa-a6646f673347", "is_bot": false, "ts": 229000, "event": "BotKill", "pixel_x": 565.09, "pixel_y": 564.39}, {"user_id": "d69f4477-9adf-46e3-9aaa-a6646f673347", "is_bot": false, "ts": 229000, "event": "BotKill", "pixel_x": 566.44, "pixel_y": 563.91}, {"user_id": "d69f4477-9adf-46e3-9aaa-a6646f673347", "is_bot": false, "ts": 232000, "event": "Position", "pixel_x": 565.85, "pixel_y": 558.79}, {"user_id": "d69f4477-9adf-46e3-9aaa-a6646f673347", "is_bot": false, "ts": 237000, "event": "Position", "pixel_x": 560.57, "pixel_y": 567.35}, {"user_id": "d69f4477-9adf-46e3-9aaa-a6646f673347", "is_bot": false, "ts": 237000, "event": "Loot", "pixel_x": 560.75, "pixel_y": 567.15}, {"user_id": "d69f4477-9adf-46e3-9aaa-a6646f673347", "is_bot": false, "ts": 237000, "event": "Loot", "pixel_x": 560.75, "pixel_y": 567.15}, {"user_id": "d69f4477-9adf-46e3-9aaa-a6646f673347", "is_bot": false, "ts": 237000, "event": "Loot", "pixel_x": 560.75, "pixel_y": 567.15}, {"user_id": "d69f4477-9adf-46e3-9aaa-a6646f673347", "is_bot": false, "ts": 237000, "event": "Loot", "pixel_x": 560.75, "pixel_y": 567.15}, {"user_id": "d69f4477-9adf-46e3-9aaa-a6646f673347", "is_bot": false, "ts": 241000, "event": "Loot", "pixel_x": 550.63, "pixel_y": 574.47}, {"user_id": "d69f4477-9adf-46e3-9aaa-a6646f673347", "is_bot": false, "ts": 241000, "event": "Loot", "pixel_x": 550.63, "pixel_y": 574.47}, {"user_id": "d69f4477-9adf-46e3-9aaa-a6646f673347", "is_bot": false, "ts": 242000, "event": "Position", "pixel_x": 549.11, "pixel_y": 576.04}, {"user_id": "d69f4477-9adf-46e3-9aaa-a6646f673347", "is_bot": false, "ts": 247000, "event": "Position", "pixel_x": 529.19, "pixel_y": 580.9}, {"user_id": "d69f4477-9adf-46e3-9aaa-a6646f673347", "is_bot": false, "ts": 262000, "event": "Position", "pixel_x": 527.62, "pixel_y": 586.02}, {"user_id": "d69f4477-9adf-46e3-9aaa-a6646f673347", "is_bot": false, "ts": 267000, "event": "Position", "pixel_x": 528.63, "pixel_y": 582.22}, {"user_id": "d69f4477-9adf-46e3-9aaa-a6646f673347", "is_bot": false, "ts": 271000, "event": "Loot", "pixel_x": 532.94, "pixel_y": 562.1}, {"user_id": "d69f4477-9adf-46e3-9aaa-a6646f673347", "is_bot": false, "ts": 272000, "event": "Position", "pixel_x": 532.95, "pixel_y": 563.16}, {"user_id": "d69f4477-9adf-46e3-9aaa-a6646f673347", "is_bot": false, "ts": 275000, "event": "Loot", "pixel_x": 530.31, "pixel_y": 572.07}, {"user_id": "d69f4477-9adf-46e3-9aaa-a6646f673347", "is_bot": false, "ts": 277000, "event": "Position", "pixel_x": 525.72, "pixel_y": 576.61}, {"user_id": "d69f4477-9adf-46e3-9aaa-a6646f673347", "is_bot": false, "ts": 281000, "event": "Loot", "pixel_x": 525.87, "pixel_y": 579.11}, {"user_id": "d69f4477-9adf-46e3-9aaa-a6646f673347", "is_bot": false, "ts": 282000, "event": "Position", "pixel_x": 525.87, "pixel_y": 579.11}, {"user_id": "d69f4477-9adf-46e3-9aaa-a6646f673347", "is_bot": false, "ts": 287000, "event": "Position", "pixel_x": 534.45, "pixel_y": 580.47}, {"user_id": "d69f4477-9adf-46e3-9aaa-a6646f673347", "is_bot": false, "ts": 292000, "event": "Position", "pixel_x": 540.2, "pixel_y": 560.47}, {"user_id": "d69f4477-9adf-46e3-9aaa-a6646f673347", "is_bot": false, "ts": 297000, "event": "Position", "pixel_x": 538.8, "pixel_y": 543.72}, {"user_id": "d69f4477-9adf-46e3-9aaa-a6646f673347", "is_bot": false, "ts": 312000, "event": "Position", "pixel_x": 541.81, "pixel_y": 540.14}, {"user_id": "d69f4477-9adf-46e3-9aaa-a6646f673347", "is_bot": false, "ts": 317000, "event": "Position", "pixel_x": 538.58, "pixel_y": 542.41}, {"user_id": "d69f4477-9adf-46e3-9aaa-a6646f673347", "is_bot": false, "ts": 372000, "event": "Position", "pixel_x": 529.16, "pixel_y": 533.46}, {"user_id": "d69f4477-9adf-46e3-9aaa-a6646f673347", "is_bot": false, "ts": 376000, "event": "Loot", "pixel_x": 521.2, "pixel_y": 528.41}, {"user_id": "d69f4477-9adf-46e3-9aaa-a6646f673347", "is_bot": false, "ts": 377000, "event": "Position", "pixel_x": 523.12, "pixel_y": 527.11}, {"user_id": "d69f4477-9adf-46e3-9aaa-a6646f673347", "is_bot": false, "ts": 382000, "event": "Position", "pixel_x": 544.4, "pixel_y": 526.1}, {"user_id": "d69f4477-9adf-46e3-9aaa-a6646f673347", "is_bot": false, "ts": 388000, "event": "Position", "pixel_x": 536.84, "pixel_y": 493.32}, {"user_id": "d69f4477-9adf-46e3-9aaa-a6646f673347", "is_bot": false, "ts": 393000, "event": "Position", "pixel_x": 531.94, "pixel_y": 493.29}, {"user_id": "d69f4477-9adf-46e3-9aaa-a6646f673347", "is_bot": false, "ts": 394000, "event": "Loot", "pixel_x": 531.94, "pixel_y": 493.29}, {"user_id": "d69f4477-9adf-46e3-9aaa-a6646f673347", "is_bot": false, "ts": 398000, "event": "Position", "pixel_x": 528.31, "pixel_y": 483.82}, {"user_id": "d69f4477-9adf-46e3-9aaa-a6646f673347", "is_bot": false, "ts": 403000, "event": "Position", "pixel_x": 521.65, "pixel_y": 465.73}, {"user_id": "d69f4477-9adf-46e3-9aaa-a6646f673347", "is_bot": false, "ts": 408000, "event": "Position", "pixel_x": 516.39, "pixel_y": 458.88}, {"user_id": "d69f4477-9adf-46e3-9aaa-a6646f673347", "is_bot": false, "ts": 413000, "event": "Position", "pixel_x": 506.2, "pixel_y": 450.18}, {"user_id": "d69f4477-9adf-46e3-9aaa-a6646f673347", "is_bot": false, "ts": 418000, "event": "Position", "pixel_x": 503.42, "pixel_y": 436.19}, {"user_id": "d69f4477-9adf-46e3-9aaa-a6646f673347", "is_bot": false, "ts": 423000, "event": "Position", "pixel_x": 496.9, "pixel_y": 426.66}, {"user_id": "d69f4477-9adf-46e3-9aaa-a6646f673347", "is_bot": false, "ts": 428000, "event": "Position", "pixel_x": 486.97, "pixel_y": 399.35}, {"user_id": "d69f4477-9adf-46e3-9aaa-a6646f673347", "is_bot": false, "ts": 433000, "event": "Position", "pixel_x": 474.61, "pixel_y": 381.21}, {"user_id": "d69f4477-9adf-46e3-9aaa-a6646f673347", "is_bot": false, "ts": 438000, "event": "Position", "pixel_x": 467.84, "pixel_y": 373.4}, {"user_id": "d69f4477-9adf-46e3-9aaa-a6646f673347", "is_bot": false, "ts": 443000, "event": "Position", "pixel_x": 455.28, "pixel_y": 366.99}, {"user_id": "d69f4477-9adf-46e3-9aaa-a6646f673347", "is_bot": false, "ts": 448000, "event": "Position", "pixel_x": 441.61, "pixel_y": 358.67}, {"user_id": "d69f4477-9adf-46e3-9aaa-a6646f673347", "is_bot": false, "ts": 453000, "event": "Position", "pixel_x": 444.51, "pixel_y": 341.51}, {"user_id": "d69f4477-9adf-46e3-9aaa-a6646f673347", "is_bot": false, "ts": 458000, "event": "Position", "pixel_x": 438.63, "pixel_y": 343.77}, {"user_id": "d69f4477-9adf-46e3-9aaa-a6646f673347", "is_bot": false, "ts": 463000, "event": "Position", "pixel_x": 438.15, "pixel_y": 322.87}, {"user_id": "d69f4477-9adf-46e3-9aaa-a6646f673347", "is_bot": false, "ts": 468000, "event": "Position", "pixel_x": 433.97, "pixel_y": 310.0}, {"user_id": "d69f4477-9adf-46e3-9aaa-a6646f673347", "is_bot": false, "ts": 473000, "event": "Position", "pixel_x": 458.89, "pixel_y": 309.46}, {"user_id": "d69f4477-9adf-46e3-9aaa-a6646f673347", "is_bot": false, "ts": 478000, "event": "Position", "pixel_x": 468.67, "pixel_y": 331.11}, {"user_id": "d69f4477-9adf-46e3-9aaa-a6646f673347", "is_bot": false, "ts": 483000, "event": "Position", "pixel_x": 484.28, "pixel_y": 324.36}, {"user_id": "d69f4477-9adf-46e3-9aaa-a6646f673347", "is_bot": false, "ts": 488000, "event": "Position", "pixel_x": 484.13, "pixel_y": 347.18}, {"user_id": "d69f4477-9adf-46e3-9aaa-a6646f673347", "is_bot": false, "ts": 493000, "event": "Position", "pixel_x": 489.33, "pixel_y": 377.4}, {"user_id": "d69f4477-9adf-46e3-9aaa-a6646f673347", "is_bot": false, "ts": 498000, "event": "Position", "pixel_x": 472.03, "pixel_y": 382.55}, {"user_id": "d69f4477-9adf-46e3-9aaa-a6646f673347", "is_bot": false, "ts": 503000, "event": "Position", "pixel_x": 462.06, "pixel_y": 370.97}, {"user_id": "d69f4477-9adf-46e3-9aaa-a6646f673347", "is_bot": false, "ts": 507000, "event": "BotKill", "pixel_x": 449.45, "pixel_y": 373.79}, {"user_id": "d69f4477-9adf-46e3-9aaa-a6646f673347", "is_bot": false, "ts": 508000, "event": "Position", "pixel_x": 447.79, "pixel_y": 374.97}, {"user_id": "d69f4477-9adf-46e3-9aaa-a6646f673347", "is_bot": false, "ts": 513000, "event": "Position", "pixel_x": 429.74, "pixel_y": 394.19}, {"user_id": "d69f4477-9adf-46e3-9aaa-a6646f673347", "is_bot": false, "ts": 518000, "event": "Position", "pixel_x": 425.92, "pixel_y": 407.9}, {"user_id": "d69f4477-9adf-46e3-9aaa-a6646f673347", "is_bot": false, "ts": 523000, "event": "Position", "pixel_x": 431.8, "pixel_y": 411.07}, {"user_id": "d69f4477-9adf-46e3-9aaa-a6646f673347", "is_bot": false, "ts": 525000, "event": "Loot", "pixel_x": 434.0, "pixel_y": 410.73}, {"user_id": "d69f4477-9adf-46e3-9aaa-a6646f673347", "is_bot": false, "ts": 528000, "event": "Position", "pixel_x": 436.62, "pixel_y": 412.57}, {"user_id": "d69f4477-9adf-46e3-9aaa-a6646f673347", "is_bot": false, "ts": 533000, "event": "Position", "pixel_x": 410.27, "pixel_y": 456.64}, {"user_id": "d69f4477-9adf-46e3-9aaa-a6646f673347", "is_bot": false, "ts": 538000, "event": "Position", "pixel_x": 426.78, "pixel_y": 469.34}, {"user_id": "d69f4477-9adf-46e3-9aaa-a6646f673347", "is_bot": false, "ts": 543000, "event": "Position", "pixel_x": 444.81, "pixel_y": 489.09}, {"user_id": "d69f4477-9adf-46e3-9aaa-a6646f673347", "is_bot": false, "ts": 548000, "event": "Position", "pixel_x": 457.17, "pixel_y": 499.33}, {"user_id": "d69f4477-9adf-46e3-9aaa-a6646f673347", "is_bot": false, "ts": 553000, "event": "Position", "pixel_x": 475.7, "pixel_y": 512.83}, {"user_id": "d69f4477-9adf-46e3-9aaa-a6646f673347", "is_bot": false, "ts": 558000, "event": "Position", "pixel_x": 483.92, "pixel_y": 526.23}, {"user_id": "d69f4477-9adf-46e3-9aaa-a6646f673347", "is_bot": false, "ts": 563000, "event": "Position", "pixel_x": 490.77, "pixel_y": 537.99}, {"user_id": "d69f4477-9adf-46e3-9aaa-a6646f673347", "is_bot": false, "ts": 569000, "event": "Position", "pixel_x": 499.21, "pixel_y": 566.35}, {"user_id": "d69f4477-9adf-46e3-9aaa-a6646f673347", "is_bot": false, "ts": 574000, "event": "Position", "pixel_x": 512.2, "pixel_y": 586.45}, {"user_id": "d69f4477-9adf-46e3-9aaa-a6646f673347", "is_bot": false, "ts": 579000, "event": "Position", "pixel_x": 527.09, "pixel_y": 601.96}, {"user_id": "d69f4477-9adf-46e3-9aaa-a6646f673347", "is_bot": false, "ts": 584000, "event": "Position", "pixel_x": 534.2, "pixel_y": 608.27}, {"user_id": "d69f4477-9adf-46e3-9aaa-a6646f673347", "is_bot": false, "ts": 589000, "event": "Position", "pixel_x": 564.02, "pixel_y": 604.58}, {"user_id": "d69f4477-9adf-46e3-9aaa-a6646f673347", "is_bot": false, "ts": 594000, "event": "Position", "pixel_x": 592.71, "pixel_y": 598.55}, {"user_id": "d69f4477-9adf-46e3-9aaa-a6646f673347", "is_bot": false, "ts": 599000, "event": "Position", "pixel_x": 609.18, "pixel_y": 576.1}, {"user_id": "d69f4477-9adf-46e3-9aaa-a6646f673347", "is_bot": false, "ts": 604000, "event": "Position", "pixel_x": 618.2, "pixel_y": 558.41}, {"user_id": "d69f4477-9adf-46e3-9aaa-a6646f673347", "is_bot": false, "ts": 609000, "event": "Position", "pixel_x": 625.21, "pixel_y": 550.26}, {"user_id": "d69f4477-9adf-46e3-9aaa-a6646f673347", "is_bot": false, "ts": 614000, "event": "Position", "pixel_x": 636.51, "pixel_y": 563.37}, {"user_id": "d69f4477-9adf-46e3-9aaa-a6646f673347", "is_bot": false, "ts": 619000, "event": "Position", "pixel_x": 644.97, "pixel_y": 568.11}, {"user_id": "d69f4477-9adf-46e3-9aaa-a6646f673347", "is_bot": false, "ts": 624000, "event": "Position", "pixel_x": 641.19, "pixel_y": 567.37}, {"user_id": "d69f4477-9adf-46e3-9aaa-a6646f673347", "is_bot": false, "ts": 629000, "event": "Position", "pixel_x": 643.12, "pixel_y": 560.49}]